LICENSE
MANIFEST.in
README.rst
requirements.txt
setup.py
django_mymigrate.egg-info/PKG-INFO
django_mymigrate.egg-info/SOURCES.txt
django_mymigrate.egg-info/dependency_links.txt
django_mymigrate.egg-info/top_level.txt
mymigrate/__init__.py
mymigrate/management/__init__.py
mymigrate/management/commands/__init__.py
mymigrate/management/commands/mymigrate.py