Metadata-Version: 1.1
Name: django-mymigrate
Version: 0.1.1
Summary: django-mymigrate is a wrapper on south that allows to quickly migrate all project apps with one command.
Home-page: https://github.com/hellpain/django-mymigrate
Author: hellpain
Author-email: urchenko88@gmail.com
License: BSD License
Platform: UNKNOWN
Classifier: Environment :: Web Environment
Classifier: Framework :: Django
Classifier: Intended Audience :: Developers
Classifier: License :: OSI Approved :: BSD License
Classifier: Operating System :: OS Independent
Classifier: Programming Language :: Python
Classifier: Programming Language :: Python :: 2.6
Classifier: Programming Language :: Python :: 2.7
Classifier: Topic :: Internet :: WWW/HTTP
Classifier: Topic :: Internet :: WWW/HTTP :: Dynamic Content
